packagepaths/__init__.py
packagepaths-0.0.1.dist-info/METADATA
packagepaths-0.0.1.dist-info/WHEEL
packagepaths-0.0.1.dist-info/top_level.txt
packagepaths-0.0.1.dist-info/RECORD
