Metadata-Version: 2.1
Name: packagepaths
Version: 0.0.1
Summary: packagepaths
